[
  {
    "full_name": "ALT-F4-LLC/kickstart.nix",
    "stargazers_count": 171,
    "open_issues_count": 12,
    "forks_count": 35
  },
  {
    "full_name": "stefandtw/quickfix-reflector.vim",
    "stargazers_count": 343,
    "open_issues_count": 2,
    "forks_count": 18
  },
  {
    "full_name": "j-hui/fidget.nvim",
    "stargazers_count": 1984,
    "open_issues_count": 21,
    "forks_count": 58
  },
  {
    "full_name": "tools-life/taskwiki",
    "stargazers_count": 840,
    "open_issues_count": 135,
    "forks_count": 95
  },
  {
    "full_name": "Canop/broot",
    "stargazers_count": 10710,
    "open_issues_count": 215,
    "forks_count": 236
  },
  {
    "full_name": "smoka7/multicursors.nvim",
    "stargazers_count": 487,
    "open_issues_count": 11,
    "forks_count": 15
  },
  {
    "full_name": "stevearc/oil.nvim",
    "stargazers_count": 3970,
    "open_issues_count": 80,
    "forks_count": 118
  },
  {
    "full_name": "sts10/rust-command-line-utilities",
    "stargazers_count": 677,
    "open_issues_count": 2,
    "forks_count": 28
  },
  {
    "full_name": "FormidableLabs/groqd",
    "stargazers_count": 230,
    "open_issues_count": 34,
    "forks_count": 16
  },
  {
    "full_name": "antfu-collective/ni",
    "stargazers_count": 6408,
    "open_issues_count": 16,
    "forks_count": 209
  },
  {
    "full_name": "pkgxdev/pkgx",
    "stargazers_count": 8973,
    "open_issues_count": 49,
    "forks_count": 1363
  },
  {
    "full_name": "iway1/react-ts-form",
    "stargazers_count": 2042,
    "open_issues_count": 25,
    "forks_count": 37
  },
  {
    "full_name": "epwalsh/obsidian.nvim",
    "stargazers_count": 4104,
    "open_issues_count": 153,
    "forks_count": 189
  },
  {
    "full_name": "nullchilly/fsread.nvim",
    "stargazers_count": 137,
    "open_issues_count": 0,
    "forks_count": 1
  },
  {
    "full_name": "google/react-schemaorg",
    "stargazers_count": 486,
    "open_issues_count": 13,
    "forks_count": 19
  },
  {
    "full_name": "AstroNvim/AstroNvim",
    "stargazers_count": 12691,
    "open_issues_count": 3,
    "forks_count": 929
  },
  {
    "full_name": "type-challenges/type-challenges",
    "stargazers_count": 43044,
    "open_issues_count": 30551,
    "forks_count": 4676
  },
  {
    "full_name": "pmndrs/react-three-fiber",
    "stargazers_count": 27420,
    "open_issues_count": 86,
    "forks_count": 1572
  },
  {
    "full_name": "bradtraversy/design-resources-for-developers",
    "stargazers_count": 58744,
    "open_issues_count": 0,
    "forks_count": 11502
  },
  {
    "full_name": "coding-horror/basic-computer-games",
    "stargazers_count": 10842,
    "open_issues_count": 17,
    "forks_count": 1329
  },
  {
    "full_name": "public-apis/public-apis",
    "stargazers_count": 316320,
    "open_issues_count": 373,
    "forks_count": 33715
  },
  {
    "full_name": "framer/motion",
    "stargazers_count": 23755,
    "open_issues_count": 221,
    "forks_count": 808
  }
]