[
  {
    "full_name": "stefandtw/quickfix-reflector.vim",
    "stargazers_count": 317,
    "open_issues_count": 2,
    "forks_count": 18
  },
  {
    "full_name": "j-hui/fidget.nvim",
    "stargazers_count": 1637,
    "open_issues_count": 12,
    "forks_count": 55
  },
  {
    "full_name": "tools-life/taskwiki",
    "stargazers_count": 793,
    "open_issues_count": 129,
    "forks_count": 93
  },
  {
    "full_name": "Canop/broot",
    "stargazers_count": 9842,
    "open_issues_count": 192,
    "forks_count": 222
  },
  {
    "full_name": "smoka7/multicursors.nvim",
    "stargazers_count": 286,
    "open_issues_count": 3,
    "forks_count": 9
  },
  {
    "full_name": "stevearc/oil.nvim",
    "stargazers_count": 2272,
    "open_issues_count": 37,
    "forks_count": 63
  },
  {
    "full_name": "sts10/rust-command-line-utilities",
    "stargazers_count": 457,
    "open_issues_count": 1,
    "forks_count": 19
  },
  {
    "full_name": "FormidableLabs/groqd",
    "stargazers_count": 204,
    "open_issues_count": 27,
    "forks_count": 14
  },
  {
    "full_name": "antfu/ni",
    "stargazers_count": 5408,
    "open_issues_count": 15,
    "forks_count": 183
  },
  {
    "full_name": "pkgxdev/pkgx",
    "stargazers_count": 8608,
    "open_issues_count": 33,
    "forks_count": 1352
  },
  {
    "full_name": "iway1/react-ts-form",
    "stargazers_count": 1992,
    "open_issues_count": 22,
    "forks_count": 34
  },
  {
    "full_name": "epwalsh/obsidian.nvim",
    "stargazers_count": 2145,
    "open_issues_count": 33,
    "forks_count": 110
  },
  {
    "full_name": "nullchilly/fsread.nvim",
    "stargazers_count": 136,
    "open_issues_count": 0,
    "forks_count": 1
  },
  {
    "full_name": "google/react-schemaorg",
    "stargazers_count": 457,
    "open_issues_count": 12,
    "forks_count": 24
  },
  {
    "full_name": "AstroNvim/AstroNvim",
    "stargazers_count": 11089,
    "open_issues_count": 3,
    "forks_count": 829
  },
  {
    "full_name": "type-challenges/type-challenges",
    "stargazers_count": 39154,
    "open_issues_count": 28345,
    "forks_count": 4199
  },
  {
    "full_name": "pmndrs/react-three-fiber",
    "stargazers_count": 25332,
    "open_issues_count": 59,
    "forks_count": 1437
  },
  {
    "full_name": "bradtraversy/design-resources-for-developers",
    "stargazers_count": 55314,
    "open_issues_count": 10,
    "forks_count": 11082
  },
  {
    "full_name": "coding-horror/basic-computer-games",
    "stargazers_count": 10733,
    "open_issues_count": 18,
    "forks_count": 1323
  },
  {
    "full_name": "public-apis/public-apis",
    "stargazers_count": 281004,
    "open_issues_count": 243,
    "forks_count": 30707
  },
  {
    "full_name": "framer/motion",
    "stargazers_count": 21408,
    "open_issues_count": 153,
    "forks_count": 693
  }
]